<?xml version='1.0' encoding='utf-8'?>
<document xmlns:codified="https://code.dccouncil.us/schemas/codified" xmlns:codify="https://code.dccouncil.us/schemas/codify" xmlns:xi="http://www.w3.org/2001/XInclude" id="Pub. L. 87-773">
  <num>87-773</num>
  <heading type="long">An Act to provide criminal penalties for trafficking in phonograph records bearing forged or counterfeit labels</heading>
  <meta>
    <effective>1960-09-13</effective>
    <citations>
      <citation type="law">Pub. L. 87-773</citation>
      <citation type="stat" url="https://www.gpo.gov/fdsys/pkg/STATUTE-76/pdf/STATUTE-76-Pg775.pdf">76 Stat. 775</citation>
    </citations>
  </meta>
</document>
