<?xml version='1.0' encoding='utf-8'?>
<document xmlns:ns0="http://www.w3.org/2001/XInclude" id="D.C. Law 20-211">
  <num type="law">20-211</num>
  <heading>Winter Sidewalk Safety Amendment Act of 2014</heading>
  <effective>2015-3-11</effective>
  <cites>
    <law lawId="211" period="20" url="http://lims.dccouncil.us/Download/31340/B20-0715-SignedAct.pdf"/>
    <register page="13074" vol="61"/>
  </cites>
  <history url="http://lims.dccouncil.us/Legislation/B20-0715">
    <narrative>Law 20-211, the “Winter Sidewalk Safety Amendment Act of 2014,” was introduced in Council and assigned Bill No. 20-715. The Bill was adopted on first and second readings on Oct. 28, 2014, and Nov. 18, 2014, respectively. Signed by the Mayor on Dec. 12, 2014, it was assigned Act No. 20-515 and transmitted to Congress for its review. D.C. Law 20-211 became effective on Mar. 11, 2015.</narrative>
  </history>
</document>
