<?xml version='1.0' encoding='utf-8'?>
<document xmlns:ns0="http://www.w3.org/2001/XInclude" id="D.C. Law 16-198">
  <num type="law">16-198</num>
  <heading type="short">Health Insurance Coverage for Habilitative Services for Children Act of 2006</heading>
  <meta>
    <effective>2007-03-02</effective>
    <citations>
      <citation type="law" url="./docs/16-198.pdf">D.C. Law 16-198</citation>
      <citation type="register">53 DCR 8829</citation>
    </citations>
    <history url="http://lims.dccouncil.us/Legislation/B16-0711">
      <narrative>Law 16-198, the “Health Insurance Coverage for Habilitative Services for Children Act of 2006”, was introduced in Council and assigned Bill No. 16-711, which was referred to the Committee on Consumer and Regulatory Affairs. The Bill was adopted on first and second readings on July 11, 2006, and October 3, 2006, respectively. Signed by the Mayor on October 23, 2006, it was assigned Act No. 16-493 and transmitted to both Houses of Congress for its review. D.C. Law 16-198 became effective on March 2, 2007.</narrative>
    </history>
  </meta>
</document>
