<?xml version='1.0' encoding='utf-8'?>
<document xmlns="https://code.dccouncil.us/schemas/dc-library" xmlns:cache="https://code.dccouncil.us/schemas/cache" xmlns:codified="https://code.dccouncil.us/schemas/codified" xmlns:codify="https://code.dccouncil.us/schemas/codify" xmlns:citations="https://code.dccouncil.us/schemas/citations" xmlns:macro="https://code.dccouncil.us/schemas/macro" xmlns:xi="http://www.w3.org/2001/XInclude" xmlns:xs="http://www.w3.org/2001/XMLSchema" xmlns:xsl="http://www.w3.org/1999/XSL/Transform" id="D.C. Act 25-651">
  <num type="act">25-651</num>
  <num type="bill">25-792</num>
  <heading type="short">Notarial Acts Clarification Amendment Act of 2024</heading>
  <heading type="long">To amend the Revised Uniform Law on Notarial Acts Act of 2018 to eliminate the requirement for a notary public to read and write in the language of any record on which the notary public performs a notarial act, require notarial officers to read or understand the language in which the notarial certificate is written, clarify that a notary may refuse to perform a notarial act if they cannot read or understand the language of the document being notarized or may require the signer to provide an official translation, and clarify that the training course for notary applicants must be approved but not provided by the Mayor.</heading>
  <meta>
    <introduced>2024-04-22</introduced>
    <effective projected="true">2025-03-06</effective>
    <citations>
      <citation type="act" url="https://lims.dccouncil.gov/downloads/LIMS/55220/Signed_Act/B25-0792-Signed_Act.pdf?Id=203062">D.C. Act 25-651</citation>
      <citation type="register">71 DCR 15795</citation>
    </citations>
    <history url="https://lims.dccouncil.us/Legislation/B25-0792">
      <vote date="2024-10-29" reading="First"/>
      <vote date="2024-11-12" reading="Final"/>
      <enacted>2024-12-12</enacted>
      <summary>BILL SUMMARY - As introduced Bill 25-792 would eliminate the requirement for a notary public to read and write in the language of any record on which the notary public performs a notarial act. It also clarifies that the training course for notary applicants must be approved but not provided by the Mayor and also requires notarial officers to read and write in the same language as the notarial certificate executed by the officer.</summary>
      <committee>Executive Administration and Labor</committee>
    </history>
  </meta>
  <text>BE IT ENACTED BY THE COUNCIL OF THE DISTRICT OF COLUMBIA, That this act may be cited as the "Notarial Acts Clarification Amendment Act of 2024".</text>
  <section>
    <num>2</num>
    <text>The Revised Uniform Law on Notarial Acts Act of 2018, effective December 4, 2018 (D.C. Law 22-189; D.C. Official Code § 1-1231.01 <em>et seq.</em>), is amended as follows:</text>
    <para>
      <num>(a)</num>
      <text>Section 4(b) (D.C. Official Code § 1-1231.03(b)) is amended as follows:</text>
      <para>
        <num>(1)</num>
        <text>Paragraph (2) is amended by striking the phrase "; or" and inserting semicolon in its place.</text>
      </para>
      <para>
        <num>(2)</num>
        <text>Paragraph (3) is amended by striking the period and inserting the phrase "; or" in its place.</text>
      </para>
      <para>
        <num>(3)</num>
        <text>A new paragraph (4) to read as follows:</text>
        <include lvl="1">
          <para>
            <num>(4)</num>
            <text>The notarial officer does not read or understand the language in which the certificate of notarial act is written.</text>
          </para>
        </include>
        <aftertext>.</aftertext>
      </para>
    </para>
    <para>
      <num>(b)</num>
      <text>Section 8 (D.C. Official Code § 1-1231.07) is amended by adding new paragraphs (a-1) and (a-2) to read as follows:</text>
      <include>
        <para>
          <num>(a-1)</num>
          <text>A notarial officer may refuse to perform a notarial act if the officer does not read or understand the language of the document being notarized.</text>
        </para>
        <para>
          <num>(a-2)</num>
          <text>A notarial officer may require a signer to provide a certified translation of the document being notarized.</text>
        </para>
      </include>
      <aftertext>.</aftertext>
    </para>
    <para>
      <num>(c)</num>
      <text>Section 20(d)(4) (D.C. Official Code § 1-1231.19(d)(4)) is repealed.</text>
    </para>
    <para>
      <num>(d)</num>
      <text>Section 21(c) (D.C. Official Code § 1-1231.20(c)) is amended by striking the phrase "provided by the Mayor" and inserting the phrase "approved by the Mayor" in its place.</text>
    </para>
    <para>
      <num>(e)</num>
      <text>Section 22(b) (D.C. Official Code § 1-1231.21(b)) is amended by striking the phrase "notary publics and applicants for endorsement as electronic notaries" and inserting the phrase "notary publics" in its place.</text>
    </para>
  </section>
  <section>
    <num>3</num>
    <heading proof="needed">Fiscal impact statement.</heading>
    <text>The Council adopts the fiscal impact statement in the committee report as the fiscal impact statement required by section 4a of the General Legislative Procedures Act of 1975, approved October 16, 2006 (120 Stat. 2038; D.C. Official Code § 1-301.47a).</text>
  </section>
  <section>
    <num>4</num>
    <heading proof="needed">Effective date.</heading>
    <text>This act shall take effect following approval by the Mayor (or in the event of veto by the</text>
    <text>Mayor, action by the Council to override the veto) and a 30-day period of congressional review as provided in section 602(c)(1) of the District of Columbia Home Rule Act, approved December 24, 1973 (87 Stat. 813; D.C. Official Code § 1-206.02(c)(1)).</text>
  </section>
</document>
