<?xml version='1.0' encoding='utf-8'?>
<document xmlns="https://code.dccouncil.us/schemas/dc-library" xmlns:codified="https://code.dccouncil.us/schemas/codified" xmlns:codify="https://code.dccouncil.us/schemas/codify" xmlns:xi="http://www.w3.org/2001/XInclude" id="D.C. Law 3-76">
  <num type="law">3-76</num>
  <meta>
    <effective>1980-07-01</effective>
    <citations>
      <citation type="law" url="./docs/3-76.pdf">D.C. Law 3-76</citation>
      <citation type="register">27 DCR 2409</citation>
    </citations>
    <search-text>r COUNCIL OF THE DISTRICT OF CO Lu MBIA NOTICE D.C. LAW 3-76 "Distr-ict of Columbia Ar-chitectur-al Bar e s ct of 19 80 Pursuant to Section 412 of the District of Colu.~bia Self- Government ar..d Goverr..mental Reorganization Act, P. L. 93-198 the A ct the Council of the District of Columbia Adopted Bill No. 3-108, on fir'st, amended first, and second readings, Februar-y 19, 1980, Apr-11 1, 1980 and April 22, 1980, respectively. Following the signatu:c-e of the Mayor- on May 14, 1980 this legislation was assigned Act No. 3-187, published in the May 6, 198: edition of the D.C. Register Vol. 27 page 2409) and tr-ar smi t tec to Congr-ess on May 15, 1980 fo~ a 30-day r-eview, in accor- dar.ce with Section 602 (c)(l) of the Act be Council of the Dist:c-ict of Columbia hereby gives notice that the 30-day Cong:c-ess onal Review Per-iod has expired, and, therefor-e, cites this enactment as D.C. LAW 3-76, effective July l, 1980. ARRI NG TON IXON Chairman of the Council Dates Counted Du:c-ing the 30-day Congr-essional Review Period: May 15,16,19,20,21,22,28,29,30 June 2,3,4,5,6,9,10,ll,12,13,16,17,l8,19,20,23, 24,25,26,27,30 D.C. lAW 3- 7 r JUL 0 l 19gQ A 'I ~c r D.C. ACT 3 1 8 7 I THE :OJN:I'L JF THE DISTRICT 1JF CJLJl-'3I.\ MAY 1 4 1980 ro est.3olish minimum raauireTiem:s for the ?l i minatiori Jf 3rchitectur31 oarriers tJ tna gt;nvsically ti-'ln:Ji:a:)oaa i ri ne•l v-:oristructej• 3lterach an::l :onverte::l JUJl ic Juil:Jinqs in 'tne District Jf CJlJmJia. 3E [T E N ~CTEJ 3Y T~E CJU'ICIL a~ T~E J IS T~t:r aF o u ~9 [ A• TM3t. t,i; 3Ct nav Je cited as the "District Jf CJlumoi3 e 2 F i n :J i q s Tha :oun:il Jf t:ie District Jf CJl.Jmoii finas th3t. acJri gt;mic 3nd SJCi31 life of tna city if not imJe:Je:J oy 1ar"riers t.J tneir noJility Jst ouilJi,qs uSaa bv c:na CODIF!O l'T"!CN D.C. Muru.ci?Cli Regulaticn.s :iener3I gt;uolic i, ttH Jistrict of :olunoi3 dJ ,ot -iffora 2- Ju i 1 l i i q s 3 1 re 3 av a r ac tea i n 3 cc Jr l 3 1 c i t n tr 3 j i t i Jn l :J esi:in st3na3r::ls• it is rel:itivelY' i1el oen s ive tJ insure tna JOliti::al jurisaictiJns in tie ma'1".ro;Jolita1 :H:d• t;ie Jistri:t of :olu~Oi3 is no~ tna Jnly one tnat does nJt n~ve le~is13tivalv :n3cted ~ini~un st~ndaras for o3rrier-fr:e lesi~n ana cJnstruction. Se 3. tha uistrict of :olumtJia naraaftar citaa as tna Bu il ainq :o::le effactive Saotencar 21, 1~77 (0.C. La 2-l8; titla 5A-l O.C.R is :lmendej 35 fJllo s al A naw Article 15 is a::ldea at tna ana tnaraof to re3a as follJws ARrr:L: t5 se:rro~ L5JO.O s:a~E A~O GENERAL RE~JI~E~E~T Sac ti Jn s l 5 0 J L S o J e l50J.2 Cis:&amp;gt;l3y of Accessi gt;ility 5ynoJl. 11 T1e purJose of this article is to raaJire tiat 31 I Juiljinqs, structures. 3nd orenises hiC1 3r~ Jsaa 01 tha ~eieral gt;u:&amp;gt;l ic ana wnicn are raq~l 3taa nv tnis CJOd Je ~3ae -3- 3i l Jnvsic3lly h:3n li:aJoed oerso,s T i e tern 'h:3n li i:Joea' ne3ns 1311 i iq :3 t:O t 3 l :ir oart 3 1 imJ airnent natner it be cenoor3ry :ir pernaneit if tie n3nu3l, Jrtnooeaic isual, auditory, Jr Other fun:tio1 tn:3t Jrevents 3 pH·so, frJm totdl :i:cess to pnysi:3l stru:tJres 4itnin nis or ier ~nviro~ment Sec• l 5 JO. 2 Jisolav Jf A:cessi:&amp;gt;ility Svm:&amp;gt;ol 8Jildin~s aid structures neetin~ the reJuirements of tne J3rrier-free desiqn soecifiC:3tio1s of t~is 3rticle s1:3 l l earlv :lisolay tn: intern:3tiona1 syno:il of :Jccess io il it for tne n3ndic3pJed SECTIJN 1501·0 P~LrC~BrLITY S ?Ct i Jn S l50l.t G~ner31 Aocl i aJi 1 i ty 150t.2 New Construction 1501 .3 1so 1 Otner Code ~eouirements t50L.5 Exenocions 1501 E~ceocions s~c. isn.1 "T1is 3rti::le i;n3ll 3C&amp;gt;Jlv to tny OJilain structure ir imJrJv~a 3re 31C t,e l3nO 3pJurten3nt thereto. aMnea or 1~ 3s ea Dy cne Jistri:t of :otu~Oid• Jr a ori~ately a~ned o r -4- r:o or JSad ov tha qeneral ouolic. Jy oerso,s visitin Jr ami sas f:&amp;gt;r 3ny ra:3sori. or JV 40 gt;r mJra Jersons amJ l Jvac tnerai .1 sec. 1501.2 ~e onstruction T~is 3rticl~ sndll aooly to all ouilain:;s 3nd struCtJras f:&amp;gt;r w~ich an 3PoliC3tion for ouilJi1g oernit #as fil?.1 ifter tne effective jate of tne Ji strict of :olu~oi 3 ~rcnitactural 3arriers Act of lq~o. axistiiq ouilainq gt;r structure s1all oa cansiaereo new :onstructi gt;n of 3nj JV itself 3nj sn3 l J therafJre Jy reJuir~a t:&amp;gt onoly witn tne or:&amp;gt;visiois of tnis article S ec l 5 J l 3 ~uiljinqs ~ltere gt;r CJn~ertad T,is artic l e snal I aoolv to OJi l ainqs or structJras il terej Jr c:&amp;gt;nvertaa f:&amp;gt;r wni en 31 apJl i cat.io'1 for oui l ai 1Q Jermit w3s filed 3fter tne effecti~e dita Jf tne Distric t gt; f Jf t.'1e alter3tio1 or CJnversion ex:eaas fifty (SJ car:e nt structJre 3t tne c:&amp;gt;m~encement gt;f tie alter3tio1 or :onversiJn. nojifv t1 oeneral orovisi:&amp;gt;ns for all Juil1i iqs re:;ulate1 ov al -5- this CJaa t c l e sia l l o i Stru e .j to a"o i c C:&amp;gt;nfl ic t i i:.n c r n 1s ar 1 lt;O JrJvisioiS of t his C~oe; n::Jwever. in c3se gt;f c:&amp;gt; nfl i c t Y gt;r:&amp;gt;visiois of this article 5 .ial l aJp ly unless in ex ceot1Jn S ec l 5 J l 5 Exemotio1s T1e pro~isi~ns Jf tnis 3rticle sn~ll not ~poly to tie t o~ildinqs and f3cil i ties gt;w1ej ov tie unite 2 3} sin~le :me 3n:j tw gt; fanilv a ellin~s 4) nist:&amp;gt;ric structure s aaternine1 ov tne Historic Jr:&amp;gt;visio1 of tie soecific 3ccess faat ur e c3nnot oe a: nieveJ 3utnanti:ity and historic v~lue of t i e structure 5 6 l• 3 oarnit 3po li c3t ioi 1s fi l aa wit i1 :Jr e3r f::illo~i:iq tie effective cHta if tie 3Ct 1nJ e urej io1 i thin oie ya3r Jf filin q ontr3:t for aesiqn; and "3. t,e aooli:ant SJOnits a1 3ffi1ri-1ii ooy. th3t t1e c:&amp;gt;ntract ~35 in effact in or oefore tie a f fective j3te of tna act. and t,3t i:tia Jesi:;in SJOni ttaa I P:H"ni ts qr31tad undar trii s suJsaci:i :Jn 5) sri~ l 1 n:Jt o 6) affective jate of tha Ji strict of :olunoia Arcn i tect.Jr3 l 3arriers Act or Lq~o. provided t1at 3 Jermit is secure ithin one vaar followinq tne effe:tiva date or the 3ct ermits ~r3nte:J :Jnjer this suosectio1 (6) sh:ill '10t Je "Sac. L51l.6 -7 x: e :Jt.io n SE:rro~ 1512.0 REOJI~E~E~TS ACCO~OIN~ ro TVPE JF o:CJPAN:v sec ti Jns "1502.L L-1 l 5 0 2 2 L l Jc:uaancv Se3tin c:oTim~d3tions. It i l } All puol i 3raas sn.3 1 1 Je m3oe 3c es sio l e t. J 3nj us~ole ov onvsically nanaicaJoaa parso1s 2) At least l oedrJon ~nit of aver1 50 oeoroJm 3) triro~qnout t1e r3n~e of size u'll itY Md price of i:ne tY J 5 ec. l 5 2. 2 ll All puoli Jse .3reas sn3ll Je accessiJle r:o 2 a- j i str i Juted Jroo:&amp;gt;rt i gt;nal l y t·ir·Ju:jtiJut 31 l tyJe5 Jf u 1 its 3) r,e prooortio1 of dJdrtnent unics fJr Jhvsic~lly h3n1i:3ooeo oarsons wni 3re efficiency gt;r l• 2. tna s3id units i, tha 3Pdrtment :onple nunoer of aoartmant units dlloc:tte:J for Dhysic3lly gt;fferej in t,e e,tire :oTiplex. tne 3J3rtnent units fJr J rwsic3lly h3nji:a:Joaa s1all r:fle::t tie ty;Ja of aJartne'1t "Sec. 15J2.3 1 Occ~p3ncv S:aci1a Acc:&amp;gt;mno~ati:&amp;gt;ns l Pla:es gt;f ass:molv icn fixaa saat i ig ~rranqements snail orovije vie~iiq pJsitiois f:&amp;gt;r p:rsois ii C dO dC it V Jf A 5 s am l y So 3Ca 'lu no er of "i i nq os i t i JO 't:J 25 2 "26 t:J 50 3 "5 l t:J 75 4 "70 t:J 100 5 "101 to 150 0 "151 to 2JO 7 "201 to 300 30 l co 4)0 9 "c.Q L co 5JO LO 51J l to lJOJ 3 of roca I "ovar l JOJ 2~ plus l t'or l 0 J JV 2 r l~OJ 2) sn :i l I Je J ra-1 i le::l in a r e aso1ao l 3n:l :a n v ni en t s2ct 1J n o r s e :t i o1s a f t~a f3: il it y av 2i t n :r o r J otri o f n 2 ro ll J i n:i ne tnOdS: Proviainq Jort30le seats wit, st3tio1arv 3) T-,es.a DJS it i 0'1S snal 1 Je loc3taa SJ 35 noi: to interf:ra ~ie.n e o rass frJm :m y ra~ of sa3ts. snall oe reachable ov Tieans Jf 3n ac:e s si o l e J atn u s i1c r3mJs 31d e 1 e~3tors or Jotn ~nere r ?c J ire j 3 1 0 sn3ll ~ot infrinqe uoon aisle r e~uiram~nts 3) r,ere snall be no steJ·s in the lis l :s or in e.n: 3c:ess route tJ tna Jerfornanca ~iawin~ Jositions islas l:3ji 1q to yiawin~ oositions for tna n3ndiC30Je::l snall '10t a~=edd a or3jient of l i1c oer foJt 310 wit 1 Je.,e l ol :itfarms 3t 30 foot i-itar als se:rro~ t503.Q c:EssrBrLITY S:cti ons t 5 0 3 l R 3m J s t503.2 Builainq ~c:ess 1503.3 Doors and Ooo rw dys 1503.c. Stai rs t 5 0 3 5 I a J r s lJ 15 0 3 J CJrri Jars Sac 1 5 J 3 l ~a np s. If l L fo:Jt i, 12 faet• snall be :Jf n:J less tnai f eet cJe3r 2 ne3surad fron cne surf3ca :Jf tne r3mJ, and l 1/4 tJ l l/2 in:n Cianecer Jr widen. tn3t are sn0Jt1. a1a t1ac ~x ce1a 01 e 3 4) E3cn r3TIO sn3l l n3 3 le"el Jl 3tform 3t th too nic1 is at le3st 5 feet by 5 feat if 3 lO:Jr 5 i1qs :iuc Jnto t1e p13tf:JrTI :Jr t:Jwdrj tna r3TIO• le"el Jl3tfo r m at le3St 3 fe et dee'J 3nj 5 feet w id a i f t'1e joJr CJes iot swinq Jnto tne pl3tfJr~ Jr tJwara cna r3no. In eit:ier inst.3nce. tne ol3tfo,-m snal l extanj ~t 1 a3st 2i. in:nes oey:Jnj tha sije of the jo:ir w'1i:h s~iigs Jut 5) E3cn ra-no snal 1 ti3ve 3t 1 e~st 5 feet Jf str3iq1t level cle3r3nce at its gt;ase 11 6 Jn: Jr mJr: leve l J l 3 t f orms 3 t i 1 t 3 r a 1 s o f o t nor e t a s ac L 5 :n 2 3uil:li1Q Access ll to and use~ole ov Jhvsically nanai:3J03d perso1s fron t n: uninterr~otej Jy steoS• 30ruot qr3aient chan~es Jr ocnar JOstru: t.i ons. Al l e Tierq ~ncv eqrass joJrs nust oa ac: ess iol Oy the han~icaJped 2 } :ncr:m:e usa~la "JY h3n:Jicaooea oarso1s snail Of Jn a lav: l 19 S :c l 5 J 3 3 l) OJors lea:Jinq tJ :xit in puOlic araas J f in nJtal ano mJtel units and 3J3rtnent units a1 1Jcataa tJ Jf nJ nore t1~1 8.5 JOunjs in cne :3se of Jutsid3 JOJrs ~nJ 10 mJra tnan 5 OJu~as in tne case Jf iisiae JOJrs. \.OJD or -12 2 th~m a1d t1e prinary door gt;f not l ass tn3n 7~ i n:nas ne3suraa fron thair closed positions. antr3nce doors i lesticulas s all n:n: conflict i th c1e swinq of t.1e vastiJule aoors 3 l 4 l joors sn3ll 1ave a minimum nei~nt of lJ incnes. Jossiole. Jut in no :as.a s;-iall nava 3 ,eiq:it excae ii1q 5/ 3 narkinJs on the q l ass co preve1~ a:c i aants S~c. 15J3.4 St3irs Stairs SM311 :onforn to t1e aoorooriate section of c~is l) Stair risers for reJuir?a eqrass st~irs le-3Cinq .JO•ara tJw~rci ~n eJ(it snall Je closed• sloJe:1 out 3nJ ~icnout saJarej Jr snarply oroje:tin osi~q. J3Se of tn2 riser Jelo sur f3c2s o r 1osi1q s 2 13- in:hes niqn 35 me3sured from tne tre3d 3t tha f3Ce of tn2 riser. rt 3 Stairs sn3ll ~a~e at le3st Jna continJous 31dr3il tn3t extends dt le3st 12 in:nas oay:J&amp;lt;id tl"'la toJ riser 3nj oevond t.,e Cotto~ risar. 310 care snoula oe t3&amp;lt;e th3t tie e(tensiJn is ~ot in a.,d of itself a naz3rj 4) Steos sri31 1 na v e risers wni:n CJ iot c 2 d I l inches. 19 '5ac. l5J3.5 FlJors Fl oJrs Jn a qivan level s1all o 3t a cjm~on level tnrouqno~t or snal 1 na~e a maximJm qr3ji?.nt of 2 par c2nt here Jr3ct i ca~le. wnere 2 floJr SJrraces Jf differe.,t 1-a els m?et• an elevator or oroo r r~mJ follJw i n:i the soacif i c3t io1 s est30 lisned in se:tio1 1 507 .o of t:hiS C gt;c2 snal I Je oro.;ictect orridors. NE(caot 35 orovijej Jelo cJrrijors m~st dve oee1 3 nininun :lear •ijtn Jf 60 incnes l r It l riere i t is nJt pra:tic3 l tJ ~rJvi c 3 c i n:n CJrri1ar, t1is re~uiramant n~y Je met Dv ar~v iain t i1 tna :orr ic Jr• jire:tio11s 3 Corri jars sar11i nq not mJre than 3 a el 1 i n::js 5 ac l S J 3 7 I a ant i f i at i on l iaanti fy aoors 1 aaji nq t:&amp;gt; ouol ic f3ci 1 iti~s 3nj amar:;e;cv suJsacti on l) sri~l 1 oa 1 ocatej 31: a h i qnt from 3 taet co 5 feat fron tMa floor• a'la fron in:nas to 12 i~c;es frJm tne 3 nic~ ni~ht gt;rove Ja'lqerous if a ol i;o oersori ~ere t:&amp;gt; ax it Jr eritar cv them n3ll oe maaa ~uic&amp;lt;lv ia:ntifi3ole co t:.T"I 15 bl T\e l 3st se1tan:e o f Se i 01 :i03.:i f :1 e ~J1 I 1 a~ e is 3menaej to raa:l ~s fJllo s T J ~va r o ne 1 s s e r :l i ff a r an: es i n 1 2" a 1 r 3 11 o s i t JS;d C) Section 0J8.2 of tne duilji1q Cade is anendad tJ re3a as follows R'lmJS sriall M-'111? slooes not qre3t=r t'1a .1 L foo t i 1 L2 feat d l Section o ll .4 of the 3uilji1q Code is anendec as fol l ows L) fhe title is anended tJ re~d as fol l Jws oll.4 Turnstiles and Cne:k-out L3nas 2) rna entire p3r3araon i~ reaesi~n~tao as oaraqr~ori "{l) Tur,sti les" anc t,e fol lo~ i 1g sante1cas are 1 er e t -l r s t i 1 e s 3 r a J roviaac 35 reouir ac e~its for o ,vsi:a\ly ia nc ic3P Je:l Jers ons tu rnstiles nust oro~ i Je 3~ inches cle3r wi a t n 35 tne turnstile rotates 3nj tne oass3ga sn3ll oe cle3r ly n 3 r 1&amp;lt; ea w i t t n a i n t e r n a t i o n 3 1 s v no o l o f a c e s s i o i 1 i t y 3) fhe followin oara r30 2) is i .1s a rt e j 2 i c ,es l!l el The first. sante ca Jf sactiJn o2oolJ(5 of t a 3ui l li1q Coaa is anenaaa to re3a as fo l lows 5 r~aieit would otnar~ise e~caea ona foJt r isa in 12 feat rui Cfl Tne sacon:1 sentence of se:"tio1 o,2'l·l2 of cne 3uil'.li1q Coda is anenaaa to read as follows s~c, ranos. w,ere eTioloye'.l• snal 1 slooe not over l fOJt. i1 l2 feet• 3:ia sriall ba surfacaa OY 3 ,o,-sl ip matari3l 30JrJvaa for tiat ourcose ql T:ie Taole of Contents of t:.na 3ui l l i 1q GJaa is aman:1e'.l gt;y a'.ldinq tne followinq Jr:Jvisions at tna an'.l th e r ~of ie:tion 15JO.O Sc JO a ie:tio1 L5Jt o Aoolic3Cil i t. v se:ti on lSJZ 0 ~e:Jui ramant:.s ACCJr::li:iq tJ TyJe Jc:uoa 1cy e:tio1 t5J3 0 Ac essioi 1 itv of affectiv uqust 2 1~72 (Raq. 12-1 title SC-2 J is anendad Oy aaaiiq t:ie fJl l o~iio n aw section 211 211 ~R:HITECTU~AL 3A~RIE~ FREE O~SIG EJU[RE~ENTS 2 l l l 5c JO a -17 9.i i lcin~s a1a structur e s ~o"ern c ov 3r i1 cr 3 l )3rrie r f r e aasiq.1 re~uiraments of ~rti:la 15 of tna 3uilji1q Code• siall oa Jesi~nea i1 :onolidn:e wit1 tn~ reJuirements of tnis s~ction 211-2 Toilet Roo11s P JOli: toilet roans snall oa 3c:essiole t.o 1Jhvsic3lly 1anaic3ooej Jers::ms and snall neat t1e reouire11ents Jf t'1is se:tio1 rr3ffi: Ld"les "T oilet rooms sh311 nave S-Ja:e t.J 3110 tr3ffi: Jf O i c es i n C! i a 11e t e r sh a 1 1 o e D r o" i J e :l i t n n o i n t e r f H en e from t.1e s~i~q of cna Joor 1ere w3tar closat s~3lls are proviaeJ. at 1e3st one st.all for Jtiysic3l ly h.andicaooea oerso1s s:ia1 l orovi Je fJr ~neelc1air a:cess from eit1er the frJnt or t.ne sioe Jf t::e a t e r 1 gt; s a t T:ie st.all snall h3va 3 11ininun iJt1 Jf oJ rf 3 door to t:ie :lear ooaninq of not: lass th3n 32 in:nes. nininun :lear floor soace of 42 in:nes i:i front JF t1e stall II l sn al l Je not lass tti :3 n 42 in:h as l gt;n 32 in: n as aJ o"e Ci Jarallal to tha fl:&amp;gt;or. ext.anji1q 3t le:3st 24 incnes 1n fro.,t of tne w3tar closet• Each tnn:ir3i l sh311 Je l l/2 i ic1es Jutsida ji3met.ar witn ~o mora th3n l 112 iic~es :laara1c: Jetwaen r3il 3nd w3ll. 3ncnorej so 35 to sJSt3in 3 liv 10 30 :Jf 300 p gt;unas 2 e1tar 1 i ne l8 i 1c:-ies fr gt;m o:ie w31 I 3nj sn~l 1 ria11e a s 3t lti to 2J in :has aoo11e t1e floor. Joo rs I~ 3 tnr e snolj i s us e 1 tn: sills sn3Jl e not mor: tn3n 5/3 in heiqnt 3nj 1a..ie 1e11ele~ edqes. rn orria~r 1~3di1q i 1to 3 toi l :t r gt;on s n3l l l"l.311e a minimum cle3r iid tn o f 36 i ri c1es. Je 3 minimum of 24 i1c1es of m~n:u..ieri iq s gt;a:e fJr ~naelciairs 3d1a:en~ t:&amp;gt; cne l3cc1 si1e of th: encr3nce dJOr Jf tne toilet room if th3t aoor s-in4s t:&amp;gt;worj ~ha jire:tio1 gt;f e1t.rv l L:h13tor i as ~TJilet rooms sn3l 1 nawe dt 1~3St Jn: la11acorv wit1 i3rrJw 3JrJns. h3vin~ 3 c1 ~3 r3nc: Jt 27 in:nes ~e3sureJ trJm -1 Jutl a ts 5h3 1 1 ot a x:eaa 120 a aq r e as F or e~oos a a r J t tar i nes 3nj 1r3iris S,311 ba fully insu13ted a&amp;gt irrors 3nd Shelves "w,ei nirrors 3nJ snelves 3ra JrJviaea• 3t l aast Oi e ni rror 31d oie snelf sn3ll oa o l 3caa 3Jove l av3tor i es ~t 3 ieiqnt nJt tJ ax:eaa 4 0 i n cha s 3oOve tie f l oor, ne :t S J r aa frJm tie Ootton Jf tne mirror f TJ i l et r ooms h i e on t :i i1 Jr i n3ls sn 311 1a ve at J e3sr Jn urin3l ~nicn is aitnar 3 w3ll-TI0Jntej elonq3te::1 ty Je #ith t.,e ooe n i1q o f tna JdS i n iot nore t1an l7 i1 c1es frJm t h a fl JO r or 3 st 3 1 1 t y oe u r i n 3 I i r h t 1e 1 i p 3 r. f l JO r l evel Ta #e l ~ac J&amp;lt; s :ina J i so a n s ers T J i l e t r a om s s n 3 l l n a "e a r: I e 3 s i J n a t o e I r a k J n a r:o,.e l :1i soanser. or ot1er di soanser 3n i di soos3 l u·ii i noJnte::1 ~i~n tne niq1est ooera~i1q cJncrol loc3taa at 3 ieiqrit not to ax:eaa 40 in::nas fron cn a flJor nowar Stalls "w1ere i 1aivi&amp;lt;l ·Jdl snowef Stal l s 3ra .JrJviC~&amp;lt;J Jerc~nt Jr a mi nimum of L• siall oa jS30le cv 3nj 3c:essiole J h ysic3lly n~nji:3JD~a o a rsol"'ls. in: l Jainq JerSJns in -2 ·J- 3 J er TI 3 n? n c. 1 v- TI a i n i a i n: a non -s I i J i a r: u re w 2 t o r Jr y l s e :i t r i o r 3 i I :ne at i n i n a r e u i r 2 rn 2 n t s of 2ll-2(0)(1) sriall o~ orovid?.d• ji~ersionarv w3tar sor3y. 3nd SOiO tray sh3lJ Je p lacej ~ta neiqnt not to ex:eaa ~a incnes 3oO~e tie floor 1 1 :01trols s~all oe sinqle-laver typa i l Soacial Ao .Jl ic3tion of R~OJ i recnem:s Tie reaui renents of t'1i s se:tio1 sh:3 1 I 31 so oa 30J1 ic3ole ihere ao:Jr gt;oridta• to toil at rooils i:i :3P.:irr: m: n i inits 3n:l IOtel :3n:l not.el units 3 l lo:ati l r:o o iysi: al ly i3naic3ooe~ oersons ~ursuant to lrti: l a 15 of tna iuilJ i 1q :a:le 2 L l 3 -13 cer o:.Jnt3ins "lof3ter fJunt3i is s .1al l be IJS.=JOI e oy. an&amp;lt;J acc2ss i Jl 2 o Jnvsic3llv h3n:lic3ooea oersois. in::l..1dinq gt;ersons in n e~ 1 c 3 i r s 5 5. affe:tiv ovenoar 3. lq77 f L3w 2-3 titl 5~-l J J is a11enaed ov '3ddi1Q t1e f:&amp;gt;llo.ii1g s~cr:iJn lell(ll s c l l l l l l -21 R H IT~ C ~T JR ~L 3 R~ [ ~Q c ~E J ~SI~ N lt;EJ U R~M~ Nr s Jarrier fr~e a~siqi re~uiraments of ~rticla 15 of tna "l• To tie m3ximum e~t!nt JossiOle. interiJr a 1 v 31: J r s h i c s n 3 1 I oe i de t i f i e l 3 s u s 3 o l a J v p n y s i 3 l l v J f nJt l ass th3n 30 souare faet• wit1 3 n in inun ~i ne ns io1 of o i icies. Joanin~ Jf 32 incnes 5 3 i s a&amp;lt;l 1 t t e r s s a l l o J r o v i a a c 3 a 1 =i c n t t o 311 ca 'J co11trol Juttons 3na swit:n:s 7 3isad latters ana n~mJers sial l oa Jloc&amp;lt; l~ttars 3nj 1unOers. a minimum of l/2 intn ni q n. wit1 zz 3. rha al ev3t:)r C3D s 11 CJntai n a tal =o o'1e lo:atej io mJr= tti3n S't inches aJO'le tie f l oJr i i i::n a the re~uir=ments of section 211.1 Jf t1is :oJe 31k-uo q3rdan-t1Pa 303rtments of 2 r 3 StJries sn3ll Je e~e11ot fr:)m t1ese r~aJirenents JrJvia?d th3t 3u3rtnents 3lloc3ted to onysi:ally nand•c~cJeJ Jers)ns :onply i1 311 J-tner resoects it, the ~polic~ole reJuirements of the District of :olumoia Arc ,iteC"t Jr3 l 3arriers Act of iqgo Se 6. effective Seutamaer 21. lq77 (J L3w 2-17; title 53-2 J l is anended cy 3d1inq a naw sactiJn tJ 3rti:le 38J SwCTCHcS tJ re3d as follows ARrICLE 380 swrr s AR:HITECTU~AL 3A~RIE R~E oescG~ lE~U!R Nr 380-2J Dasiqn le~uiramenc 8Jildin~s a1d structures ~o"ernea 01 cha 3r:Miceccur~l Jarrier free desiqn re~uiraments of Article 15 of tne 3uil~i .1q CJoa. snall be ~esi ned ii :onoliance wit1 tha r~Juiremants of this section 3 23- Fr2auerit '3tid essanti 31 use. sn3l l Je olac e::i 10 ni Er t::i:ln S~ i ri C1 eS 30JV2 tna flaO re J 1isu31 alarms sh3ll e pro i::leJ 3n::l inteqr3tea wit the Jells to oe 3Cti'l3tej at tne s3me tine. Eic.it liqnts t,3t fl3SM in can junctiJn ~itn the fire 3J3rm syste~ na y Je use~ to sar"e tnis JuroJse In hJtel 3nd motel uni ts 31d 303rtnent u-,i ts 31 lo catej to p,ysi:al l y nanaic3ooe::i Jersons Jurs~ant t.J '3.rticla. l5 of ttie 3ui l::linq Code• 3 11 el ectric:31 sw i t.:n:?S sn3l l Je mourited a m3ximum o f 54 i1c 1es 30Jv~ t n e floor 3n :1 electric3l outlets s1all oe no less tn3n 1'3 inches fron r:ne fl JO r To trie m3xim~m ext&amp;lt;?nt Jf"3Ct:i:aole. in 311 Jt. 1er J uilji1qs 3nj fa:ilities suoject tJ tnis s~ction. e l ectr ic31 5 itch es 3nd ele:tri::3J aui::1e1:s sni:!ll :onolv wi t tna aravisions of Jaraqr3on (c Se 7. in Otner Areas. The 14avor shal 1 estaol isn ne:ess3r" rules 3nj r-e:4u l 3ti Jns to e1s~re tn.:it al 1 3re3s wii en 3re ooe .1 to 31d JSed ov the ~e~er3l ouol ic a na w,i:n 3re req~lated ov Jr 3re Jn1er tn antral jf tne District ~o~ern~ent oe naje -2 !t- 3c:essi D1 e tJ hysic3lly h:rn1i:aJ pe a :J? rso1s C.Jnsis lt ii r:ni s sact i Jn 3) Puoli Sije,.3lks. ro t~e e~tant Jermitted JY t gt;o gt;graJMY• ouol i: safet v 3nJ ot1er fa:t:&amp;gt;rs 3S aeter11inej Jy t1e ~3Y.Jr ouol i: sije,.3lks Sh3ll :onply witn tha Jr'.l11isions set fJ rtn i1 i:nis s u J sect i Jn l iuJlic w3ll(S snai l oe Jninterruote':l JV St eJ s 3oruo"t qradi ent n3n~es or other OJStructi gt;ns :3nj Sh:31 I 1d11e io sida s l:l o a ~r a3te r tti3n l i ·i c int incnas 3na s.1a1 1 2 :3t la3st 6J i n :nes wide :3nd n311e 3 qr3~ient J f n gt;t ~Jre t:h~ n oercent 2 mere al ks intersect th Ot. ne r w3l &amp;lt;S t'1eY sh3l l J l an1 to a c:&amp;gt;m11on level 3 uro cuts Shdl 1 10t in :310 of thams el ves o 3 CJrJ :ucs sn3l l be oe11ele1 to Street le 11e l i r.h :3 naxirnun 3llo aole lio gt;f lt2 incn Ol P3r~ inq L.Jts. rn 31 1 0:3r&amp;lt;inQ lots 3nd ~araoes nare Jers ons Jark t 1eir Jw~ 11e1i:les. J3rking S03ces s13Jl oe set 3siae :3nj i aentifiaa 3S reservea f gt;r 01ysic3J lv 13ndiC:3oae1 JersJns Jnly 25- to feder3l OJi lain~s or :ti3nceries are exenot fr m t"1es2 re iui remants• J3r~in~ lot for tne JurDoSe of tnis suosecti Jn 2) In o~r~inq lJts that h3Ve at least tJ out ioc for use JY o,vsi:ally ~andic3ooej Jersons 03rkin~ spaces jje,tif ie j for exc l Jsive JSe )y the onvsic31ly n3ndi:aooed s,all oe ice less tnan L2 feet SD3Ces m3y oe 9 feet wide if tnev 3re locate~ iext to 3n sh31 l oe loclted as ne3r as oossiole to cne 3c:essio l e entrances of t~e oui ldin~ or facil itv servea heel 3Cross m3i1 craffi: J3nes or Oehinj :ars to re3c 2 ates sh3 ll iot Je 1Jc3tec wit1i, tn2 reJuirea m2 a1s of 3c:ess fJr o,ysi:3l l y n3ndic3pJe1 JerS)ns C) Puo l i feleohJnes. {l uolic coin teleJhonas s1all oa ful l y 3ccessible tJ oersJns in ~neel:n3irs wit~ 311 co:itrols loc3tej no more th3n 54 inches 3~0~e tie floJr wnere 4neelc13ir cJnfi1ej ~sars nave 3 siaa re~ci Jr 4~ i n:nas ii~n wnere tie ta1apnone must Je 3aoro3cne~ Jy front31 re 3C n Zl TeleJnonas snail be :onp3tiOle wi tn 1e~rin 3jj5 nj if 03n&amp;lt;S of teleJMJn s are o rov i je 5 p2r :e 1~ cut io lass ttBn one ii 3 ouildinq or fa:ility s:iall oa ea.JiJoad ~itn VJl.Jme :01trol d) Liorary Stacks• Aisles. rna i lti Jetwaei l i Jr3ry &amp;gt;t3C&amp;lt;s s1al l 02 io lass tn3n 32 inc1es anj the turnin~ rajius 3t tna en~ Jt t1e St3:k r'l3 l l gt;e no less t:ian ~a iic:ies e) A:cJmmodatiJns for tha ~e3rin~ ImJairea l ujicoriums, t1e3ters a otner olaces Jf ~sseTioly e~uicJej 4ith fixed sa3ti1q s13ll orovi~e f3cilitias or aevi:es to en3ola Jers:in:&amp;gt; 4itn n=3ri1q 1is3 gt;iliti~s t:&amp;gt; 03rticioite fully in t1e '3:ti11ities 1eld i1 rna ~erfJrnanc~ ca~acitv raaui~e~ of tna fa:ilii:ies or Je-1i:es ~nould c:ima ~s close as Jossiole -27 e:nno l o~y o:rn i cs co1aitio1 2) Tna faciJitias or :le-1i:es for Jers:&amp;gt;ns i tn uo to 5J 51 to lJO lOl t:&amp;gt; 50J 5'.lt t gt; 1000 tOOl to 150J J ver 15JO f) P~n31 ti es. 1'1 i n i 'l1U Tl 3 n i n i nun n i n i nun 12 n i n i nu n l 6 n i n i u n 2 0 nini~un 20 olus L fo r 300 0 11er 15JO ~nv Je rs:&amp;gt;n wno v iol ates or f3i ls tJ conoly wit1 3nv Jf finea iot nore tia~ threa nunare1jol13rs (S30J or Se a. S :ct i Jn q 7 A 3 of r c i 1 a ic I I I of :l 3 rt I o f tn i~n avs ana Traffic ~aQu13tio1s of tna Jistri:t of o 1 u :no i a f f e t i a c r i I L 7 7 R c .J 1 3 t i o :i 7 3 l 2 s :a: r -23- 3m~n::lej to r~a.:l 35 fJllo,.s its ~QJivalent, issued oy anv St :rt.e Jr 1uris::li:t io1 sr ll Je ~rantej trie soecial oarkinq Jrivileqas est30lish~d ov tn i s Sec. 9. Sever3bil itv. circumst3nce is ,eJa i ,1v3lid. tne 11ali'.1itY of tne renain::ier Sec 10. This act snall take effect after 3 t.,ir'tv (3 0) jay oeriJd of :onqressional rel/i~w fJl lowinq a:Jora11al Jy_ trie ~avor (or in tne event of veto ov tne ~avor. 3C1:ion Jy tie JrJviaea i11 sectiori !l02(C)(l) Jf tie Dis trict Jf CJlJmJi-3 aoJrJvaa Oacemoer 24• 1973 (97 Stat. 8l3i J CJda, s~c. L- l47(C)(l \ /i1 1 I I I I Mayor District of Coll.Jibia APPROVED: May 14, 1980 Cotmci.l of the District of Colt.rnbia 1 I t~eacn. Of TS~ n~ ST'.ilt f COIL~3l.ii .iemo ;Cf J.;c:m :c 1C: Bi 1 3-108 i.C ON: To Adoo t 2- 19- 80) First :\eadbg tJ;J IC l'C':Z u~n~a~n~iMm o~u s U:sea o~o~r 5e I •I I t 2\UIMCt I I l I c r t r i nT""r N I I I i l E I I I I l S F i C G 1 I I l r,rr I I I I ~L;J..SON I I I I IS l.l"t D iG I I rT .l lt I I I ~OORE I I l I n T [ i I i i t:.1~TW' I i I I l I I I I I i 1' cl. 1'~T C: I I I I c IT .l. 1 I I I I i I I 04 u z c~arr C c Y: To Adopt 1-80 l.mQpded F i ~s~ Eead ;fi~ B VCtC:t u_n_a_n_im_o_u_s sem J_a rv i_s a_n_d W i_n_t_e_r n~Yn11r I&amp;lt f J C! t r r-r .l l ~COS I I t: o11'T'IV 1 V I l rs•1 i ,r. T 7 a s r \ 4'\ t X g .l.dgpr Cu 8 0) final Reading Ci lfCtO ic u-.n a n~i lil=-o~u s e.m A_1_1 P e.s n~t c..a n 1 1 c lt;e:o-•c• 1 1 1 A c.'1 1 I 0 I Z c lt;t t </search-text>
  </meta>
  <section>
    <num>7</num>
    <codified:stub doc="D.C. Code" path="§7-1003"/>
  </section>
</document>
