<?xml version='1.0' encoding='utf-8'?>
<document xmlns:codified="https://code.dccouncil.us/schemas/codified" xmlns:codify="https://code.dccouncil.us/schemas/codify" xmlns:xi="http://www.w3.org/2001/XInclude" id="D.C. Law 6-69">
  <num type="law">6-69</num>
  <heading type="short">Youth Rehabilitation Amendment Act of 1985</heading>
  <meta>
    <effective>1985-12-07</effective>
    <citations>
      <citation type="law" url="./docs/6-69.pdf">D.C. Law 6-69</citation>
      <citation type="register">32 DCR 4587</citation>
    </citations>
    <history>
      <narrative>Law 6-69, the “Youth Rehabilitation Amendment Act of 1985,” was introduced in Council and assigned Bill No. 6-47, which was referred to the Committee on the Judiciary. The bill was adopted on first and second readings on June 25, 1985 and July 9, 1985, respectively. Signed by the Mayor on July 29, 1985, it was assigned Act No. 6-72 and transmitted to both Houses of Congress for its review.</narrative>
    </history>
  </meta>
</document>
