<?xml version='1.0' encoding='utf-8'?>
<document xmlns:codified="https://code.dccouncil.us/schemas/codified" xmlns:codify="https://code.dccouncil.us/schemas/codify" xmlns:xi="http://www.w3.org/2001/XInclude" id="Pub. L. 93-229">
  <num>93-229</num>
  <heading type="long">An act to amend Chapter 33 of Title 28 of the District of Columbia Code, relating to usury, and for other purposes</heading>
  <meta>
    <effective>1973-12-29</effective>
    <citations>
      <citation type="law">Pub. L. 93-229</citation>
      <citation type="stat" url="https://www.gpo.gov/fdsys/pkg/STATUTE-87/pdf/STATUTE-87-Pg945.pdf">87 Stat. 945</citation>
    </citations>
  </meta>
</document>
