<?xml version='1.0' encoding='utf-8'?>
<document xmlns="https://code.dccouncil.us/schemas/dc-library" xmlns:codified="https://code.dccouncil.us/schemas/codified" xmlns:codify="https://code.dccouncil.us/schemas/codify" xmlns:xi="http://www.w3.org/2001/XInclude" id="D.C. Law 18-315">
  <num type="law">18-315</num>
  <heading type="short">Alternative Money Lending and Services Reform Amendment Act of 2010</heading>
  <meta>
    <effective>2011-03-12</effective>
    <citations>
      <citation type="law" url="./docs/18-315.pdf">D.C. Law 18-315</citation>
      <citation type="register">57 DCR 12412</citation>
    </citations>
    <history url="http://lims.dccouncil.us/Legislation/B18-0715">
      <narrative>Law 18-315, the “Alternative Money Lending and Services Reform Amendment Act of 2010”, was introduced in Council and assigned Bill No. 18-715, which was referred to the Committee on Public Services and Consumer Affairs. The Bill was adopted on first and second readings on November 9, 2010, and November 23, 2010, respectively. Signed by the Mayor on December 9, 2010, it was assigned Act No. 18-636 and transmitted to both Houses of Congress for its review. D.C. Law 18-315 became effective on March 12, 2011.</narrative>
    </history>
  </meta>
</document>
