<?xml version='1.0' encoding='utf-8'?>
<document xmlns:cache="https://code.dccouncil.us/schemas/cache" xmlns:citations="https://code.dccouncil.us/schemas/citations" xmlns:codified="https://code.dccouncil.us/schemas/codified" xmlns:codify="https://code.dccouncil.us/schemas/codify" xmlns:macro="https://code.dccouncil.us/schemas/macro" xmlns:xi="http://www.w3.org/2001/XInclude" xmlns:xs="http://www.w3.org/2001/XMLSchema" xmlns:xsl="http://www.w3.org/1999/XSL/Transform" xmlns="https://code.dccouncil.us/schemas/dc-library" id="D.C. Law 23-164">
  <num type="law">23-164</num>
  <num type="bill">23-854</num>
  <num type="act">23-461</num>
  <heading type="short">RPP Voluntary Exclusion Temporary Act of 2020</heading>
  <heading type="long">To provide the Mayor, on a temporary basis, the authority to make a property ineligible for residential parking permits when it is a condition of a zoning order.</heading>
  <meta>
    <introduced>2020-07-20</introduced>
    <effective>2020-12-23</effective>
    <temporary/>
    <citations>
      <citation type="law" url="https://lims.dccouncil.us/downloads/LIMS/45419/Signed_Act/B23-0854-Signed_Act.pdf">D.C. Law 23-164</citation>
      <citation type="register">67 DCR 13232</citation>
    </citations>
    <history url="https://lims.dccouncil.us/Legislation/B23-0854">
      <vote date="2020-07-23" reading="First"/>
      <vote date="2020-09-22" reading="Final"/>
      <enacted>2020-11-02</enacted>
      <summary/>
      <committee>Retained by the Council</committee>
    </history>
  </meta>
  <text>BE IT ENACTED BY THE COUNCIL OF THE DISTRICT OF COLUMBIA, That this act may be cited as the "RPP Voluntary Exclusion Temporary Act of 2020".</text>
  <!-- <codify:insert doc="D.C. Code" path="50" after="25B" history="false">
    <container>
      <prefix>Chapter</prefix>
      <num>25C</num>
      <heading>Residential Parking Permit Voluntary Exclusion.</heading>
    </container>
  </codify:insert> -->
  <section>
    <!-- <codify:insert doc="D.C. Code" path="50|25C" num-value="50-2561"/> -->
    <num>2</num>
    <heading>RPP voluntary exclusion.</heading>
    <para>
      <num>(a)</num>
      <text>The Mayor may, when a condition of a zoning order, designate a property, including its future residents, as ineligible to obtain residential parking permits.</text>
    </para>
    <para>
      <num>(b)</num>
      <text>Before entering into a purchase and sales agreement or lease, an owner of a property that has been designated as ineligible to obtain residential parking permits pursuant to subsection (a) of this section shall:</text>
      <para>
        <num>(1)</num>
        <text>Provide written notice of the designation to a buyer or residential tenant; and</text>
      </para>
      <para>
        <num>(2)</num>
        <text>Require the buyer or residential tenant to acknowledge receipt of the notice required by paragraph (1) of this subsection in writing.</text>
      </para>
    </para>
    <para>
      <num>(c)</num>
      <text>Upon designating a property ineligible to obtain residential parking permits pursuant to subsection (a) of this section, the Mayor shall record with the recorder of deeds a restrictive covenant identifying any such property as ineligible for residential parking permits.</text>
    </para>
    <para>
      <num>(d)</num>
      <para>
        <num>(1)</num>
        <text>Failure of a property owner to provide written notice of a residential tenant's inability to obtain a residential parking permit associated with the property shall be grounds for the tenant to be released from obligations under the rental agreement.</text>
      </para>
      <para>
        <num>(2)</num>
        <text>Failure of a property owner to provide written notice of a buyer's inability to obtain a residential parking permit associated with the property shall be considered a material breach of the purchase and sales agreement.</text>
      </para>
    </para>
    <codify:temporary doc="D.C. Code" path="§50-2552" action="creation of § 50-2561"/>
      <!-- <codify:insert doc="D.C. Code" path="§50-2561" before="heading" history="false" display-template="">
        <text>
      *NOTE: This section was created by temporary legislation that will expire on August 5, 2021.*
      </text>
      </codify:insert> -->
  </section>
  <section>
    <num>3</num>
    <heading>Fiscal impact statement.</heading>
    <text>The Council adopts the fiscal impact statement of the Budget Director as the fiscal impact statement required by section 4a of the General Legislative Procedures Act of 1975, approved October 16, 2006 (120 Stat. 2038; D.C. Official Code § 1-301.47a).</text>
  </section>
  <section>
    <num>4</num>
    <heading>Effective date.</heading>
    <para>
      <num>(a)</num>
      <text>This act shall take effect following approval by the Mayor (or in the event of veto by the Mayor, action by the Council to override the veto), a 30-day period of congressional review as provided in section 602(c)(1) of the District of Columbia Home Rule Act, approved December 24, 1973 (87 Stat. 813; D.C. Official Code § 1-206.02(c)(1)), and publication in the District of Columbia Register.</text>
    </para>
    <para>
      <num>(b)</num>
      <text>This act shall expire after 225 days of its having taken effect.</text>
    </para>
  </section>
</document>
